step_hen/__init__.py
step_hen/presentation.py
step_hen/schutzenbergergraph.py
step_hen/stephen.py
step_hen/wordgraph.py
step_hen-0.0.3.dist-info/LICENSE
step_hen-0.0.3.dist-info/METADATA
step_hen-0.0.3.dist-info/WHEEL
step_hen-0.0.3.dist-info/top_level.txt
step_hen-0.0.3.dist-info/RECORD
