Metadata-Version: 2.1
Name: step_hen
Version: 0.0.3
Summary: A rudimentary implementation of Stephen's procedure for inverse monoids.
Home-page: https://github.com/james-d-mitchell/step_hen
Author: James D. Mitchell, Maria Tsalakou
Author-email: jdm3@st-andrews.ac.uk, mt200@st-andrews.ac.uk
License: GPL3
Platform: any
Classifier: Development Status :: 4 - Beta
Classifier: Environment :: Console
Classifier: Intended Audience :: Developers
Classifier: License :: OSI Approved :: GNU General Public License v3 (GPLv3)
Classifier: Operating System :: POSIX
Classifier: Operating System :: MacOS
Classifier: Operating System :: Unix
Classifier: Operating System :: Microsoft :: Windows
Classifier: Programming Language :: Python
Classifier: Programming Language :: Python :: 3
Classifier: Topic :: Software Development :: Libraries :: Python Modules
License-File: LICENSE
